<featureType>
  <id>FeatureTypeInfoImpl-51f2513c:16558b05d32:-7fee</id>
  <name>gefahrenhinweiskarte_stfv.durchgangsstrassen</name>
  <nativeName>durchgangsstrassen</nativeName>
  <namespace>
    <id>NamespaceInfoImpl-51f2513c:16558b05d32:-7ffc</id>
  </namespace>
  <title>gefahrenhinweiskarte_stfv.durchgangsstrassen</title>
  <abstract>Der Störfallverordnung unterstellte Durchgangsstrassen (Gefahrenhinweiskarte Störfälle)</abstract>
  <keywords>
    <string>features</string>
    <string>durchgangsstrassen</string>
    <string>achsnummer\@vocabulary=search\;</string>
  </keywords>
  <nativeCRS class="projected">PROJCS[&quot;CH1903+ / LV95&quot;, 
  GEOGCS[&quot;CH1903+&quot;, 
    DATUM[&quot;CH1903+&quot;, 
      SPHEROID[&quot;Bessel 1841&quot;, 6377397.155, 299.1528128, AUTHORITY[&quot;EPSG&quot;,&quot;7004&quot;]], 
      TOWGS84[674.374, 15.056, 405.346, 0.0, 0.0, 0.0, 0.0], 
      AUTHORITY[&quot;EPSG&quot;,&quot;6150&quot;]], 
    PRIMEM[&quot;Greenwich&quot;, 0.0, AUTHORITY[&quot;EPSG&quot;,&quot;8901&quot;]], 
    UNIT[&quot;degree&quot;, 0.017453292519943295], 
    AXIS[&quot;Geodetic longitude&quot;, EAST], 
    AXIS[&quot;Geodetic latitude&quot;, NORTH], 
    AUTHORITY[&quot;EPSG&quot;,&quot;4150&quot;]], 
  PROJECTION[&quot;Oblique_Mercator&quot;, AUTHORITY[&quot;EPSG&quot;,&quot;9815&quot;]], 
  PARAMETER[&quot;longitude_of_center&quot;, 7.439583333333333], 
  PARAMETER[&quot;latitude_of_center&quot;, 46.952405555555565], 
  PARAMETER[&quot;azimuth&quot;, 90.0], 
  PARAMETER[&quot;scale_factor&quot;, 1.0], 
  PARAMETER[&quot;false_easting&quot;, 2600000.0], 
  PARAMETER[&quot;false_northing&quot;, 1200000.0], 
  PARAMETER[&quot;rectified_grid_angle&quot;, 90.0], 
  UNIT[&quot;m&quot;, 1.0], 
  AXIS[&quot;Easting&quot;, EAST], 
  AXIS[&quot;Northing&quot;, NORTH], 
  AUTHORITY[&quot;EPSG&quot;,&quot;2056&quot;]]</nativeCRS>
  <srs>EPSG:2056</srs>
  <nativeBoundingBox>
    <minx>2595483.57042272</minx>
    <maxx>2644757.39871679</maxx>
    <miny>1215391.77601339</miny>
    <maxy>1260692.50435077</maxy>
    <crs class="projected">EPSG:2056</crs>
  </nativeBoundingBox>
  <latLonBoundingBox>
    <minx>7.378684026989167</minx>
    <maxx>8.032589256143268</maxx>
    <miny>47.08802394184562</miny>
    <maxy>47.49697773394174</maxy>
    <crs>EPSG:4326</crs>
  </latLonBoundingBox>
  <projectionPolicy>NONE</projectionPolicy>
  <enabled>true</enabled>
  <metadata>
    <entry key="recalculate-bounds">true</entry>
    <entry key="cachingEnabled">false</entry>
  </metadata>
  <store class="dataStore">
    <id>DataStoreInfoImpl-51f2513c:16558b05d32:-7ffb</id>
  </store>
  <maxFeatures>0</maxFeatures>
  <numDecimals>0</numDecimals>
  <attributes>
    <attribute>
      <name>achseid</name>
      <minOccurs>0</minOccurs>
      <maxOccurs>0</maxOccurs>
      <nillable>false</nillable>
      <binding>java.math.BigDecimal</binding>
    </attribute>
    <attribute>
      <name>achsname</name>
      <minOccurs>0</minOccurs>
      <maxOccurs>0</maxOccurs>
      <nillable>false</nillable>
      <binding>java.lang.String</binding>
    </attribute>
    <attribute>
      <name>achsnummer</name>
      <minOccurs>0</minOccurs>
      <maxOccurs>0</maxOccurs>
      <nillable>false</nillable>
      <binding>java.lang.String</binding>
    </attribute>
    <attribute>
      <name>achstyp</name>
      <minOccurs>0</minOccurs>
      <maxOccurs>0</maxOccurs>
      <nillable>false</nillable>
      <binding>java.lang.String</binding>
    </attribute>
    <attribute>
      <name>achstypnam</name>
      <minOccurs>0</minOccurs>
      <maxOccurs>0</maxOccurs>
      <nillable>false</nillable>
      <binding>java.lang.String</binding>
    </attribute>
    <attribute>
      <name>eigentueme</name>
      <minOccurs>0</minOccurs>
      <maxOccurs>0</maxOccurs>
      <nillable>false</nillable>
      <binding>java.lang.String</binding>
    </attribute>
    <attribute>
      <name>enddistanz</name>
      <minOccurs>0</minOccurs>
      <maxOccurs>0</maxOccurs>
      <nillable>false</nillable>
      <binding>java.math.BigDecimal</binding>
    </attribute>
    <attribute>
      <name>laenge</name>
      <minOccurs>0</minOccurs>
      <maxOccurs>0</maxOccurs>
      <nillable>false</nillable>
      <binding>java.math.BigDecimal</binding>
    </attribute>
    <attribute>
      <name>modified</name>
      <minOccurs>0</minOccurs>
      <maxOccurs>0</maxOccurs>
      <nillable>false</nillable>
      <binding>java.lang.String</binding>
    </attribute>
    <attribute>
      <name>modifiedby</name>
      <minOccurs>0</minOccurs>
      <maxOccurs>0</maxOccurs>
      <nillable>false</nillable>
      <binding>java.lang.String</binding>
    </attribute>
    <attribute>
      <name>segmentid</name>
      <minOccurs>0</minOccurs>
      <maxOccurs>0</maxOccurs>
      <nillable>false</nillable>
      <binding>java.math.BigDecimal</binding>
    </attribute>
    <attribute>
      <name>segmentnr</name>
      <minOccurs>0</minOccurs>
      <maxOccurs>0</maxOccurs>
      <nillable>false</nillable>
      <binding>java.math.BigDecimal</binding>
    </attribute>
    <attribute>
      <name>startdista</name>
      <minOccurs>0</minOccurs>
      <maxOccurs>0</maxOccurs>
      <nillable>false</nillable>
      <binding>java.math.BigDecimal</binding>
    </attribute>
    <attribute>
      <name>ogc_fid</name>
      <minOccurs>0</minOccurs>
      <maxOccurs>0</maxOccurs>
      <nillable>false</nillable>
      <binding>java.math.BigDecimal</binding>
    </attribute>
    <attribute>
      <name>durchg</name>
      <minOccurs>0</minOccurs>
      <maxOccurs>0</maxOccurs>
      <nillable>false</nillable>
      <binding>java.math.BigDecimal</binding>
    </attribute>
    <attribute>
      <name>geometrie</name>
      <minOccurs>0</minOccurs>
      <maxOccurs>0</maxOccurs>
      <nillable>false</nillable>
      <binding>com.vividsolutions.jts.geom.MultiLineString</binding>
    </attribute>
  </attributes>
  <overridingServiceSRS>false</overridingServiceSRS>
  <skipNumberMatched>false</skipNumberMatched>
  <circularArcPresent>false</circularArcPresent>
</featureType>